naive_tokenizers/__init__.py
naive_tokenizers/abstract_tokenizer.py
naive_tokenizers/bert_tokenizer.py
naive_tokenizers/bert_tokenizer_test.py
naive_tokenizers/jieba_tokenizer.py
naive_tokenizers/jieba_tokenizer_test.py
naive_tokenizers/tokenizer.py
naive_tokenizers/transformer_tokenizer.py
naive_tokenizers/transformers_tokenizer_test.py
naive_tokenizers-0.0.1.dist-info/LICENSE
naive_tokenizers-0.0.1.dist-info/METADATA
naive_tokenizers-0.0.1.dist-info/WHEEL
naive_tokenizers-0.0.1.dist-info/top_level.txt
naive_tokenizers-0.0.1.dist-info/RECORD
